<?xml version="1.0" encoding="UTF-8"?>
<DEFECTS>
  <DEFECT>
    <SFA>
      <FILEPATH>C:\Users\vanba\source\repos\QLKS\vddv\</FILEPATH>
      <FILENAME>user.h</FILENAME>
      <LINE>15</LINE>
      <COLUMN>1</COLUMN>
    </SFA>
    <DEFECTCODE>26495</DEFECTCODE>
    <DESCRIPTION>Variable 'user::node::next' is uninitialized. Always initialize a member variable (type.6).</DESCRIPTION>
    <FUNCTION>user::node::{ctor}</FUNCTION>
    <DECORATED>??0node@user@@QAE@XZ</DECORATED>
    <FUNCLINE>15</FUNCLINE>
    <ADDITIONALINFO>
      <targetSymbol>user::node::next</targetSymbol>
    </ADDITIONALINFO>
    <PATH></PATH>
  </DEFECT>
</DEFECTS>